nefertiti/__init__.py
nefertiti/datetime_assistant.py
nefertiti/env_assistant.py
nefertiti/excel_assistant.py
nefertiti/filein/__init__.py
nefertiti/filein/csv_loader.py
nefertiti/filein/html_loader.py
nefertiti/filein/xls_loader.py
nefertiti/filein/xlsx_loader.py
nefertiti/fileout/__init__.py
nefertiti/fileout/example.py
nefertiti/fileout/xlsxout.py
nefertiti/sqlcli/__init__.py
nefertiti/sqlcli/base_sql_client.py
nefertiti/sqlcli/mssql_client.py
nefertiti/sqlcli/psql_client.py
nefertiti/sqlcli/sqlite3_client.py
nefertiti/sqlcli/transaction_cursor.py
nefertiti-0.0.1.dist-info/METADATA
nefertiti-0.0.1.dist-info/WHEEL
nefertiti-0.0.1.dist-info/top_level.txt
nefertiti-0.0.1.dist-info/RECORD
