Metadata-Version: 2.1
Name: nefertiti
Version: 0.0.1
Summary: 高频业务的套路实现
Home-page: https://github.com/sunxianliang/nefertiti
Author: sunxianliang
Author-email: sunxianliang.cn@gmail.com
License: UNKNOWN
Platform: UNKNOWN
Classifier: Development Status :: 3 - Alpha
Classifier: Programming Language :: Python
Classifier: Programming Language :: Python :: 3.6
Classifier: Programming Language :: Python :: 3.7
